pyloid/__init__.py
pyloid/autostart.py
pyloid/base_ipc/base.py
pyloid/base_ipc/event_api.py
pyloid/base_ipc/window_api.py
pyloid/browser_window.py
pyloid/custom/titlebar.py
pyloid/filewatcher.py
pyloid/ipc.py
pyloid/monitor.py
pyloid/pyloid.py
pyloid/rpc.py
pyloid/serve.py
pyloid/store.py
pyloid/thread_pool.py
pyloid/timer.py
pyloid/tray.py
pyloid/url_interceptor.py
pyloid/utils.py
pyloid-0.27.2.dist-info/LICENSE
pyloid-0.27.2.dist-info/METADATA
pyloid-0.27.2.dist-info/WHEEL
pyloid-0.27.2.dist-info/RECORD
