Metadata-Version: 2.3
Name: pyloid
Version: 0.27.2
Summary: 
Author: aesthetics-of-record
Author-email: 111675679+aesthetics-of-record@users.noreply.github.com
Requires-Python: >=3.9,<3.14
Classifier: Programming Language :: Python :: 3
Classifier: Programming Language :: Python :: 3.9
Classifier: Programming Language :: Python :: 3.10
Classifier: Programming Language :: Python :: 3.11
Classifier: Programming Language :: Python :: 3.12
Classifier: Programming Language :: Python :: 3.13
Requires-Dist: aiofiles (>=24.1.0,<25.0.0)
Requires-Dist: aiohttp-cors (>=0.8.1,<0.9.0)
Requires-Dist: pickledb (>=1.3.2,<2.0.0)
Requires-Dist: platformdirs (>=4.3.7,<5.0.0)
Requires-Dist: pyside6 (==6.9.2)
